setup.py
savemodel/__init__.py
savemodel.egg-info/PKG-INFO
savemodel.egg-info/SOURCES.txt
savemodel.egg-info/dependency_links.txt
savemodel.egg-info/not-zip-safe
savemodel.egg-info/requires.txt
savemodel.egg-info/top_level.txt