Metadata-Version: 1.0
Name: savemodel
Version: 0.1
Summary: To save models to HDFS
Home-page: http://github.com
Author: Yogesh Somawar
Author-email: yogesh.somawar@qio.io
License: MIT
Platform: UNKNOWN
